{
  "store": [
    {
      "id": 1,
      "name": "Storyt",
      "description": "super store"
    }
  ],
  "projects": [
    {
      "id": 1,
      "storeId": 1,
      "name": "Build a React App"
    },
    {
      "id": 2,
      "storeId": 1,
      "name": "Create a Form"
    }
  ],
  "tasks": [
    {
      "id": 1,
      "projectId": 1,
      "description": "Use Vite to create a basic React app"
    },
    {
      "id": 2,
      "projectId": 1,
      "description": "Install React Router and setup routes"
    },
    {
      "id": 3,
      "projectId": 2,
      "description": "Create a form with 5 input fields"
    }
  ]
}
